{
  "Home/Utilities": [
    "Mortgage/Rent",
    "Body Corporate Fees",
    "Council Rates",
    "Furniture/Appliances",
    "Renovations & Home Improvement",
    "Electricity",
    "Gas",
    "Water",
    "Internet",
    "Home phone",
    "Mobile"
  ],
  "Transport": [
    "Public Transport",
    "Petrol",
    "Tolls & Parking",
    "Rego & Licence",
    "Maintenance",
    "Fines"
  ],
  "Insurance/Financial": [
    "Car Insurance",
    "Home & Contents Insurance",
    "Personal & Life Insurance",
    "Health Insurance",
    "Car Loan",
    "Credit Card Interest",
    "Investments",
    "Super Contributions",
    "Charity Donations"
  ],
  "Groceries": [
    "Supermarket",
    "Butcher",
    "Fish",
    "Fruit & Vegetables",
    "Bakery",
    "Alcohol"
  ],
  "Personal": [
    "Hobbies",
    "Clothing & Shoes",
    "Jewellery & Accessories",
    "Computers & Gadgets",
    "Sports & Gym",
    "Education",
    "Pet Care & Vet"
  ],
  "Medical": [
    "Cosmetics",
    "Hair & Beauty",
    "Pharmacy",
    "Glasses & Eye Care",
    "Dental",
    "General Medical Expense"
  ],
  "Entertainment/Eating Out": [
    "Breakfast",
    "Lunch",
    "Dinner",
    "Dessert",
    "Refreshments",
    "Bars & Clubs",
    "Books",
    "Digital Subscriptions",
    "Celebrations & Gifts",
    "Events"
  ]
}